django_loaddata_streamed-0.0.1.dist-info/licenses/LICENSE
loaddata_streamed/__init__.py
loaddata_streamed/jsons_serializer.py
django_loaddata_streamed-0.0.1.dist-info/METADATA
django_loaddata_streamed-0.0.1.dist-info/WHEEL
django_loaddata_streamed-0.0.1.dist-info/top_level.txt
django_loaddata_streamed-0.0.1.dist-info/RECORD
